globalnoc_monitoring_service_status/__init__.py
globalnoc_monitoring_service_status-0.1.0.dist-info/WHEEL
globalnoc_monitoring_service_status-0.1.0.dist-info/METADATA
globalnoc_monitoring_service_status-0.1.0.dist-info/RECORD
